{
  "categories": [
    {
      "id": 1,
      "title": "Technology BookShelf",
      "description": "Tủ sách công nghệ là tủ sách chứa những quyển sách công nghệ...",
      "imageUrl": "/public/tech-category.jpg",
      "linkCategory": "http://localhost:5173/category"
    },
    {
      "id": 2,
      "title": "Science BookShelf",
      "description": "Tủ sách khoa học là tủ sách chứa những quyển sách khoa học...",
      "imageUrl": "/public/tech-category.jpg",
      "linkCategory": "http://localhost:5173/category"
    },
    {
      "id": 3,
      "title": "History BookShelf",
      "description": "Tủ sách lịch sự là tủ sách chứa những quyển sách lịch sử...",
      "imageUrl": "/public/tech-category.jpg",
      "linkCategory": "http://localhost:5173/category"
    }
  ]
}